common/__init__.py
common/apps.py
common/migrations/__init__.py
common/models/__init__.py
common/models/achievement.py
common/models/calendar.py
common/models/charger.py
common/models/fcm.py
common/models/payment.py
common/models/route.py
common/models/user.py
common/models/valuation.py
powerpathfinder_models-2.2.0.dist-info/METADATA
powerpathfinder_models-2.2.0.dist-info/WHEEL
powerpathfinder_models-2.2.0.dist-info/top_level.txt
powerpathfinder_models-2.2.0.dist-info/RECORD
