Metadata-Version: 2.1
Name: powerpathfinder-models
Version: 2.2.0
Requires-Python: >=3.11
Requires-Dist: Django >=5.0
